Threaded_Sparse_TFIDF/TFIDF.py
Threaded_Sparse_TFIDF/Threaded_Sparse_TFIDF.py
Threaded_Sparse_TFIDF/__init__.py
Threaded_Sparse_TFIDF-0.2.dist-info/LICENSE
Threaded_Sparse_TFIDF-0.2.dist-info/METADATA
Threaded_Sparse_TFIDF-0.2.dist-info/WHEEL
Threaded_Sparse_TFIDF-0.2.dist-info/top_level.txt
Threaded_Sparse_TFIDF-0.2.dist-info/RECORD
